{"fs def":"11","invoice folder path":"_documents\\invoices\\","vat rate":"1.23","transport charges":["2.50","10.00","4.00","4.50","",""],"db user":"hct","fs lbl title":"16","db pass":"pass1234","suppliers names":["DT","TyreLeader","PWT","TyreCall","",""],"sales folder path":"_documents\\sales\\","db host":"jdbc:mysql:\/\/127.0.0.1:3306\/hct_stock","number of services":"10","lang":"eng.json","profit rate 1":"1.35","profit rate 3":"1.75","profit rate 2":"2.5","doc subfolder path":"YYYY\\MM\\DD\\","recycling charge":"3.50","profits":["20 %","50 %","125 %","200 %"],"stock folder path":"_documents\\stock\\","repak folder path":"_documents\\repak\\","default printer name":"Canon MP620 series Printer (Copy 1)","app color R":"250","app color G":"50","starting":"true","logo path":"resources\\img\\Logo HCT 245x84.png","app color B":"50","font":"Segoe UI Black"}